basetestcase/__init__.py
basetestcase/base_FormTestCase.py
basetestcase/base_FunctionalTestCase.py
basetestcase/base_ModelTestCase.py
basetestcase/base_UtilityTestCase.py
basetestcase/base_ViewTestCase.py
django_basetestcase-1.1.8.dist-info/LICENSE.txt
django_basetestcase-1.1.8.dist-info/METADATA
django_basetestcase-1.1.8.dist-info/WHEEL
django_basetestcase-1.1.8.dist-info/top_level.txt
django_basetestcase-1.1.8.dist-info/RECORD
