Metadata-Version: 2.1
Name: django-basetestcase
Version: 1.1.8
Summary: A collection of cheater methods for the Django TestCase.
Home-page: https://github.com/spleeding1/django-basetestcase
Author: Carl Brubaker
Author-email: spleeding@juno.com
License: UNKNOWN
Platform: UNKNOWN
Classifier: Programming Language :: Python :: 3
Classifier: License :: OSI Approved :: MIT License
Classifier: Operating System :: OS Independent
